chronicdb
